.gitignore
.travis.yml
LICENSE
README.rst
setup.cfg
setup.py
tox.ini
doc/Makefile
doc/make.bat
doc/source/conf.py
doc/source/index.rst
doc/source/reference/nadia.api.rst
doc/source/reference/nadia.array.rst
doc/source/reference/nadia.builder_provider.rst
doc/source/reference/nadia.common.rst
doc/source/reference/nadia.exceptions.rst
doc/source/reference/nadia.object.rst
doc/source/reference/nadia.primitives.rst
doc/source/reference/nadia.rst
doc/source/reference/nadia.schema.rst
doc/source/userdoc/tutorial.rst
nadia/__init__.py
nadia/api.py
nadia/array.py
nadia/builder_provider.py
nadia/common.py
nadia/exceptions.py
nadia/object.py
nadia/primitives.py
nadia/schema.py
nadia.egg-info/PKG-INFO
nadia.egg-info/SOURCES.txt
nadia.egg-info/dependency_links.txt
nadia.egg-info/requires.txt
nadia.egg-info/top_level.txt
tests/__init__.py
tests/test_array.py
tests/test_builder_provider.py
tests/test_common.py
tests/test_object.py
tests/test_primitives.py