Metadata-Version: 1.0
Name: nadia
Version: 0.1.5
Summary: Nadia: automatic generation of Marshmallow Schemas for OpenAPI 3 schemas.
Home-page: UNKNOWN
Author: Konrad Jałowiecki <dexter2206@gmail.com>, Magdalena Nowak
Author-email: dexter2206@gmail.com
License: MIT
Keywords: openapi schema validation
Platform: Linux
Platform: Unix
